pytest_profiles/__init__.py
pytest_profiles/plugin.py
pytest_profiles/profile.py
pytest_profiles-0.2.0.dist-info/LICENSE
pytest_profiles-0.2.0.dist-info/METADATA
pytest_profiles-0.2.0.dist-info/WHEEL
pytest_profiles-0.2.0.dist-info/entry_points.txt
pytest_profiles-0.2.0.dist-info/top_level.txt
pytest_profiles-0.2.0.dist-info/RECORD
