Metadata-Version: 2.1
Name: pytest-profiles
Version: 0.2.0
Summary: pytest plugin for configuration profiles
Home-page: https://www.github.com/stefanhoelzl/pytest_profiles/
Author: Stefan Hoelzl
Author-email: stefanh+pytest_profiles@posteo.de
License: MIT
Keywords: pytest plugin configuration config profile template
Platform: UNKNOWN
Classifier: Development Status :: 4 - Beta
Classifier: Intended Audience :: Developers
Classifier: License :: OSI Approved :: MIT License
Classifier: Programming Language :: Python :: 3
Classifier: Programming Language :: Python :: 3.7
Classifier: Programming Language :: Python :: 3.8
Classifier: Programming Language :: Python :: 3.9
Classifier: Programming Language :: Python :: 3.10
Classifier: Operating System :: MacOS :: MacOS X
Classifier: Operating System :: POSIX :: Linux
Classifier: Operating System :: Microsoft :: Windows
Classifier: Topic :: Software Development
Classifier: Topic :: Software Development :: Testing
License-File: LICENSE
Requires-Dist: pytest (>=3.7.0)
